connectify/__init__.py
connectify/configuration_services.py
connectify/datetime_services.py
connectify/enum_services.py
connectify/error_services.py
connectify/file_services.py
connectify/facebook_services/__init__.py
connectify/facebook_services/facebook_connection.py
connectify/facebook_services/tests.py
connectify/slack_services/__init__.py
connectify/slack_services/enums.py
connectify/slack_services/errors.py
connectify/slack_services/slack_connection.py
connectify/slack_services/tests.py
connectify-0.1.5.dist-info/LICENSE
connectify-0.1.5.dist-info/METADATA
connectify-0.1.5.dist-info/WHEEL
connectify-0.1.5.dist-info/top_level.txt
connectify-0.1.5.dist-info/RECORD
