Metadata-Version: 2.1
Name: connectify
Version: 0.1.5
Summary: Different Python I/O handlers
Home-page: https://github.com/muladzevitali/connectify
Author: Vitali Muladze
Author-email: muladzevitali@gmail.com
Project-URL: Bug Tracker, https://github.com/muladzevitali/connectify/issues
Classifier: Programming Language :: Python :: 3
Classifier: License :: OSI Approved :: MIT License
Classifier: Operating System :: OS Independent
Requires-Python: >=3.8
License-File: LICENSE
Requires-Dist: slack-sdk ==3.22.0
Requires-Dist: aiohttp ==3.8.5
Requires-Dist: facebook-sdk ~=3.1.0
Requires-Dist: python-dotenv ==1.0.0
